{"data":{"site":{"siteMetadata":{"author":"Miguel de Guzman","homeCity":"Philippines"}},"markdownRemark":{"html":"<br/>\n<p><strong><em>“8/16”</em></strong> </p>\n<p>I’m thinking of a monthly and weekly themed blog especially about topics I’m really digging and experimenting with and one of them that pops into my head at most (well I decide on it everyday) </p>","excerpt":"“8/16”   I’m thinking of a monthly and weekly themed blog especially about topics I’m really digging and experimenting with and one of them…","fields":{"tagSlugs":["/tags/creating-art/","/tags/philosophy/","/tags/health-and-wellness/","/tags/blog/"]},"frontmatter":{"title":"Intermittent Fasting","tags":["creating-art","philosophy","health and wellness","blog"],"date":"September 11, 2019"}}},"pageContext":{"isCreatedByStatefulCreatePages":false,"slug":"/intermittent-fasting/"}}